.gitignore
.project
.pydevproject
.readthedocs.yml
.travis.yml
CHANGES.rst
LICENSE
MANIFEST.in
README.rst
appveyor.yml
pytest.ini
setup.cfg
setup.py
tox.ini
Fuzzy.egg-info/PKG-INFO
Fuzzy.egg-info/SOURCES.txt
Fuzzy.egg-info/dependency_links.txt
Fuzzy.egg-info/requires.txt
Fuzzy.egg-info/top_level.txt
docs/conf.py
docs/history.rst
docs/index.rst
src/double_metaphone.c
src/double_metaphone.h
src/fuzzy.pyx
test/test_fuzzy.py